<?xml version="1.0" encoding="UTF-8"?>

<userB9ZL3Q xmlns:xsi="http://www.w3.org/2001/XMLSchema-instance" xsi:noNamespaceSchemaLocation="userB9ZL3Q.xsd">

<users>
  <user id="1">
    <firstname>Ádám</firstname>
	<lastname>Szivós</lastname>
	<profession>mazochista</profession>
  </user>
  
  <user id="2">
    <firstname>Béla</firstname>
	<lastname>Kiss</lastname>
	<profession>kőműves</profession>
  </user>
  
  <user id="3">
    <firstname>Béla</firstname>
	<lastname>Nagy</lastname>
	<profession>masiniszta</profession>
  </user>
</users>